{
  "main": {
    "id": "d0673b658c98d51f",
    "type": "split",
    "children": [
      {
        "id": "48e34a2b9a7b9a02",
        "type": "tabs",
        "children": [
          {
            "id": "53ef6983bb836715",
            "type": "leaf",
            "state": {
              "type": "markdown",
              "state": {
                "file": "Angular/Lesson 1 - Basics - Group Anagram/First Angular/Angular Notes 12-8.md",
                "mode": "source",
                "source": false
              }
            }
          }
        ]
      }
    ],
    "direction": "vertical"
  },
  "left": {
    "id": "c1469f275a860d67",
    "type": "split",
    "children": [
      {
        "id": "00536b146b260039",
        "type": "tabs",
        "children": [
          {
            "id": "334fbe39f4dc74fa",
            "type": "leaf",
            "state": {
              "type": "file-explorer",
              "state": {
                "sortOrder": "alphabetical"
              }
            }
          },
          {
            "id": "9fcfa49ba0955293",
            "type": "leaf",
            "state": {
              "type": "search",
              "state": {
                "query": "",
                "matchingCase": false,
                "explainSearch": false,
                "collapseAll": false,
                "extraContext": false,
                "sortOrder": "alphabetical"
              }
            }
          },
          {
            "id": "f967c29d9795cbca",
            "type": "leaf",
            "state": {
              "type": "bookmarks",
              "state": {}
            }
          }
        ]
      }
    ],
    "direction": "horizontal",
    "width": 300
  },
  "right": {
    "id": "589ab5b21042e1f9",
    "type": "split",
    "children": [
      {
        "id": "8d37da7d8b6fdc2c",
        "type": "tabs",
        "children": [
          {
            "id": "b0de26a2449058aa",
            "type": "leaf",
            "state": {
              "type": "backlink",
              "state": {
                "file": "Angular/Lesson 1 - Basics - Group Anagram/First Angular/Angular Notes 12-8.md",
                "collapseAll": false,
                "extraContext": false,
                "sortOrder": "alphabetical",
                "showSearch": false,
                "searchQuery": "",
                "backlinkCollapsed": false,
                "unlinkedCollapsed": true
              }
            }
          },
          {
            "id": "f44b4cbea4158198",
            "type": "leaf",
            "state": {
              "type": "outgoing-link",
              "state": {
                "file": "Angular/Lesson 1 - Basics - Group Anagram/First Angular/Angular Notes 12-8.md",
                "linksCollapsed": false,
                "unlinkedCollapsed": true
              }
            }
          },
          {
            "id": "7e6d06b956164567",
            "type": "leaf",
            "state": {
              "type": "tag",
              "state": {
                "sortOrder": "frequency",
                "useHierarchy": true
              }
            }
          },
          {
            "id": "111157d75d8c9d3b",
            "type": "leaf",
            "state": {
              "type": "outline",
              "state": {
                "file": "Angular/Lesson 1 - Basics - Group Anagram/First Angular/Angular Notes 12-8.md"
              }
            }
          }
        ]
      }
    ],
    "direction": "horizontal",
    "width": 300,
    "collapsed": true
  },
  "left-ribbon": {
    "hiddenItems": {
      "switcher:Open quick switcher": false,
      "graph:Open graph view": false,
      "canvas:Create new canvas": false,
      "daily-notes:Open today's daily note": false,
      "templates:Insert template": false,
      "command-palette:Open command palette": false
    }
  },
  "active": "53ef6983bb836715",
  "lastOpenFiles": [
    "Angular/Lesson 1 - Basics - Group Anagram/First Angular/What-The Key/Back-End/build/kotlin/compileKotlin/cacheable/caches-jvm/jvm/kotlin/package-parts.tab.values.at",
    "Angular/Lesson 1 - Basics - Group Anagram/First Angular/What-The Key/Back-End/build/kotlin/compileKotlin/cacheable/caches-jvm/jvm/kotlin/dirty-output-classes.tab_i.len",
    "Angular/Lesson 1 - Basics - Group Anagram/First Angular/What-The Key/Back-End/build/kotlin/compileKotlin/cacheable/caches-jvm/jvm/kotlin/dirty-output-classes.tab.len",
    "Angular/Lesson 1 - Basics - Group Anagram/First Angular/What-The Key/Back-End/build/classes/kotlin/main/com/example/WhatTheKey/MyController.class",
    "Angular/Lesson 1 - Basics - Group Anagram/First Angular/What-The Key/Back-End/build/classes/kotlin/main/com/example/WhatTheKey/WhatTheKeyApplication.class",
    "Angular/Lesson 1 - Basics - Group Anagram/First Angular/What-The Key/Back-End/build/classes/kotlin/main/com/example/WhatTheKey/WhatTheKeyApplicationKt.class",
    "Angular/Lesson 1 - Basics - Group Anagram/First Angular/What-The Key/Back-End/build/kotlin/compileKotlin/cacheable/dirty-sources.txt",
    "Angular/Lesson 1 - Basics - Group Anagram/First Angular/What-The Key/Back-End/build/kotlin/compileKotlin/cacheable/caches-jvm/jvm/kotlin/dirty-output-classes.tab_i",
    "Angular/Lesson 1 - Basics - Group Anagram/First Angular/What-The Key/Back-End/build/snapshot/kotlin/compileKotlin/2.zip",
    "Angular/Lesson 1 - Basics - Group Anagram/First Angular/What-The Key/Back-End/build/snapshot/kotlin/compileKotlin/1.zip",
    "Angular/Lesson 1 - Basics - Group Anagram/First Angular/What-The Key/Back-End/build/snapshot/kotlin/compileKotlin/0.zip",
    "Angular/Lesson 1 - Basics - Group Anagram/First Angular/What-The Key/Back-End/HELP.md",
    "Angular/Lesson 1 - Basics - Group Anagram/First Angular/What-The Key/Front-End/node_modules/@angular/compiler-cli/node_modules/@babel/core/node_modules/convert-source-map/README.md",
    "Angular/Lesson 1 - Basics - Group Anagram/First Angular/What-The Key/Front-End/node_modules/@angular/compiler-cli/node_modules/@babel/core/node_modules/semver/README.md",
    "Angular/Lesson 1 - Basics - Group Anagram/First Angular/What-The Key/Front-End/node_modules/@sigstore/sign/node_modules/minipass-fetch/node_modules/minipass/README.md",
    "Angular/Lesson 1 - Basics - Group Anagram/First Angular/What-The Key/Front-End/node_modules/webpack/node_modules/ajv-keywords/keywords/dotjs/README.md",
    "Angular/Lesson 1 - Basics - Group Anagram/First Angular/What-The Key/Front-End/node_modules/webpack/node_modules/ajv/lib/dotjs/README.md",
    "Angular/Lesson 1 - Basics - Group Anagram/First Angular/What-The Key/Front-End/node_modules/tuf-js/node_modules/minipass-fetch/node_modules/minipass/README.md",
    "Angular/Lesson 1 - Basics - Group Anagram/First Angular/What-The Key/Front-End/node_modules/terser-webpack-plugin/node_modules/ajv-keywords/keywords/dotjs/README.md",
    "Angular/Lesson 1 - Basics - Group Anagram/First Angular/What-The Key/Front-End/node_modules/terser-webpack-plugin/node_modules/ajv/lib/dotjs/README.md",
    "Angular/Lesson 1 - Basics - Group Anagram/First Angular/What-The Key/Front-End/node_modules/tar/node_modules/fs-minipass/node_modules/minipass/README.md",
    "Angular/Lesson 1 - Basics - Group Anagram/First Angular/What-The Key/Front-End/node_modules/sigstore/node_modules/minipass-fetch/node_modules/minipass/README.md",
    "Angular/Lesson 1 - Basics - Group Anagram/First Angular/What-The Key/Front-End/node_modules/send/node_modules/debug/node_modules/ms/readme.md",
    "Angular/Lesson 1 - Basics - Group Anagram/First Angular/What-The Key/Front-End/node_modules/send/node_modules/debug/node_modules/ms/license.md",
    "Angular/Lesson 1 - Basics - Group Anagram/First Angular/What-The Key/Front-End/node_modules/npm-registry-fetch/node_modules/minipass-fetch/node_modules/minipass/README.md",
    "Angular/Lesson 1 - Basics - Group Anagram/First Angular/What-The Key/Front-End/node_modules/hpack.js/node_modules/readable-stream/doc/wg-meetings/2015-01-30.md",
    "Angular/Lesson 1 - Basics - Group Anagram/First Angular/What-The Key/Front-End/node_modules/@sigstore/sign/node_modules/@tootallnate/once/README.md",
    "Angular/Lesson 1 - Basics - Group Anagram/First Angular/What-The Key/Front-End/node_modules/@schematics/angular/node_modules/@angular-devkit/core/README.md",
    "Angular/Lesson 1 - Basics - Group Anagram/First Angular/What-The Key/Front-End/node_modules/@babel/traverse/node_modules/@babel/generator/README.md",
    "Angular/Lesson 1 - Basics - Group Anagram/First Angular/What-The Key/Front-End/node_modules/@babel/plugin-transform-computed-properties/node_modules/@babel/template/README.md",
    "Angular/Lesson 1 - Basics - Group Anagram/First Angular/What-The Key/Front-End/node_modules/@babel/helpers/node_modules/@babel/template/README.md",
    "Angular/Lesson 1 - Basics - Group Anagram/First Angular/What-The Key/Front-End/node_modules/@babel/helper-wrap-function/node_modules/@babel/template/README.md",
    "Angular/Lesson 1 - Basics - Group Anagram/First Angular/What-The Key/Front-End/node_modules/@babel/helper-function-name/node_modules/@babel/template/README.md",
    "Angular/Lesson 1 - Basics - Group Anagram/First Angular/What-The Key/Front-End/node_modules/@angular-devkit/schematics/node_modules/@angular-devkit/core/README.md",
    "Angular/Lesson 1 - Basics - Group Anagram/First Angular/What-The Key/Front-End/node_modules/@angular/compiler-cli/node_modules/@babel/template/README.md",
    "Angular/Lesson 1 - Basics - Group Anagram/First Angular/What-The Key/Front-End/node_modules/@angular/compiler-cli/node_modules/@babel/generator/README.md",
    "Angular/Lesson 1 - Basics - Group Anagram/First Angular/What-The Key/Front-End/node_modules/istanbul-reports/lib/html-spa/assets/sort-arrow-sprite.png",
    "Angular/Lesson 1 - Basics - Group Anagram/First Angular/What-The Key/Front-End/node_modules/istanbul-reports/lib/html/assets/sort-arrow-sprite.png",
    "Angular/Lesson 1 - Basics - Group Anagram/First Angular/What-The Key/Front-End/node_modules/istanbul-reports/lib/html/assets/favicon.png",
    "Angular/Lesson 1 - Basics - Group Anagram/First Angular/What-The Key/Front-End/node_modules/serve-index/public/icons/page_world.png",
    "Angular/Lesson 1 - Basics - Group Anagram/First Angular/What-The Key/Front-End/node_modules/serve-index/public/icons/page_word.png",
    "Angular/Lesson 1 - Basics - Group Anagram/First Angular/What-The Key/Front-End/node_modules/serve-index/public/icons/page_white_zip.png",
    "Angular/Lesson 1 - Basics - Group Anagram/First Angular/What-The Key/Front-End/node_modules/serve-index/public/icons/page_white_wrench.png",
    "Angular/Lesson 1 - Basics - Group Anagram/First Angular/What-The Key/Front-End/node_modules/serve-index/public/icons/page_white_world.png",
    "Angular/Lesson 1 - Basics - Group Anagram/First Angular/What-The Key/Front-End/node_modules/serve-index/public/icons/page_white_word.png",
    "Angular/Lesson 1 - Basics - Group Anagram/First Angular/What-The Key/Front-End/node_modules/serve-index/public/icons/page_white_width.png"
  ]
}